llm_ir/__init__.py
llm_ir/chunks.py
llm_ir/messages.py
llm_ir/py.typed
llm_ir/roles.py
llm_ir/adapter/__init__.py
llm_ir/adapter/openai.py
llm_ir-0.0.22.dist-info/METADATA
llm_ir-0.0.22.dist-info/WHEEL
llm_ir-0.0.22.dist-info/top_level.txt
llm_ir-0.0.22.dist-info/RECORD
