Metadata-Version: 2.4
Name: llm-ir
Version: 0.0.22
Summary: Core message IR for LLM pipelines
Author: Mathis Siebert
Requires-Python: >=3.11
Requires-Dist: pydantic>=2.0
